near_pytest/__init__.py
near_pytest/client.py
near_pytest/compiler.py
near_pytest/fixtures.py
near_pytest/models.py
near_pytest/py.typed
near_pytest/sandbox.py
near_pytest/testing.py
near_pytest/utils/binary.py
near_pytest/utils/logger.py
near_pytest-1.0.0.dist-info/METADATA
near_pytest-1.0.0.dist-info/WHEEL
near_pytest-1.0.0.dist-info/entry_points.txt
near_pytest-1.0.0.dist-info/licenses/LICENSE
near_pytest-1.0.0.dist-info/RECORD
