Metadata-Version: 2.4
Name: near-pytest
Version: 1.0.0
Summary: Add your description here
License-File: LICENSE
Requires-Python: >=3.11
Requires-Dist: base58>=2.1.1
Requires-Dist: nearc>=0.8.1
Requires-Dist: py-near-fork>=0.1.1
Requires-Dist: pynacl>=1.5.0
Requires-Dist: pytest>=8.3.5
Requires-Dist: requests>=2.32.3
